Metadata-Version: 1.1
Name: rose2
Version: 1.1.0
Summary: ROSE2 python package
Home-page: https://github.com/linlabbcm/rose2
Author: UNKNOWN
Author-email: UNKNOWN
License: UNKNOWN
Download-URL: https://github.com/linlabbcm/rose2/tarball/v1.1.0
Keywords: bioinformatics,super-enhancers
Platform: UNKNOWN
